[
    [
        "I had been coming to each work",
        "maiṁ hara kama vica ā gi'ā sī",
        "ਮੈਂ ਹਰ ਕੰਮ ਵਿਚ ਆ ਗਿਆ ਸੀ",
        "I had been coming to each work",
        {
            "en-en": 0,
            "pa-en": 1,
            "pa-pa": 2,
            "en-pa": 3
        },
        {
            "form": "past",
            "continuous": true,
            "perfect": true,
            "plural": false,
            "fem": 1,
            "mas": 1
        },
        {
            "pron": "i",
            "verb": "be",
            "noun": "people",
            "det": "the",
            "adj": "first"
        }
    ],
    [
        "I had been coming to the first world",
        "maiṁ pahilē sasāra vica ā rihā sī",
        "ਮੈਂ ਪਹਿਲੇ ਸੰਸਾਰ ਵਿਚ ਆ ਰਿਹਾ ਸੀ",
        "I had been coming to the first world",
        {
            "en-en": 0,
            "pa-en": 1,
            "pa-pa": 2,
            "en-pa": 3
        },
        {
            "form": "past",
            "continuous": true,
            "perfect": true,
            "plural": false,
            "fem": 1,
            "mas": 1
        },
        {
            "pron": "i",
            "verb": "be",
            "noun": "people",
            "adj": "many"
        }
    ],
    [
        "I had been thinking about the first child",
        "maiṁ pahilē bacē bārē sōca rihā sī",
        "ਮੈਂ ਪਹਿਲੇ ਬੱਚੇ ਬਾਰੇ ਸੋਚ ਰਿਹਾ ਸੀ",
        "I had been thinking about the first child",
        {
            "en-en": 0,
            "pa-en": 1,
            "pa-pa": 2,
            "en-pa": 3
        },
        {
            "form": "past",
            "continuous": true,
            "perfect": true,
            "plural": false,
            "fem": 1,
            "mas": 1
        },
        {
            "pron": "i",
            "verb": "have",
            "noun": "business",
            "det": "a",
            "adj": "good"
        }
    ],
    [
        "I had been thinking about my many children",
        "maiṁ āpaṇē bahuta sārē baci'āṁ bārē sōca rihā sī",
        "ਮੈਂ ਆਪਣੇ ਬਹੁਤ ਸਾਰੇ ਬੱਚਿਆਂ ਬਾਰੇ ਸੋਚ ਰਿਹਾ ਸੀ",
        "I had been thinking about my many children",
        {
            "en-en": 0,
            "pa-en": 1,
            "pa-pa": 2,
            "en-pa": 3
        },
        {
            "form": "past",
            "continuous": true,
            "perfect": true,
            "plural": false,
            "fem": 1,
            "mas": 1
        },
        {
            "pron": "i",
            "verb": "have",
            "noun": "business",
            "adj": "each"
        }
    ],
    [
        "I had been thinking about the first family",
        "maiṁ pahilē parivāra bārē sōcadā rihā sī",
        "ਮੈਂ ਪਹਿਲੇ ਪਰਿਵਾਰ ਬਾਰੇ ਸੋਚਦਾ ਰਿਹਾ ਸੀ",
        "I had been thinking about the first family",
        {
            "en-en": 0,
            "pa-en": 1,
            "pa-pa": 2,
            "en-pa": 3
        },
        {
            "form": "past",
            "continuous": true,
            "perfect": true,
            "plural": false,
            "fem": 1,
            "mas": 1
        },
        {
            "pron": "i",
            "verb": "have",
            "noun": "day",
            "det": "a",
            "adj": "good"
        }
    ],
    [
        "I had been thinking about my many families",
        "maiṁ āpaṇē bahuta sārē parivārāṁ bārē sōcadā rihā sī",
        "ਮੈਂ ਆਪਣੇ ਬਹੁਤ ਸਾਰੇ ਪਰਿਵਾਰਾਂ ਬਾਰੇ ਸੋਚਦਾ ਰਿਹਾ ਸੀ",
        "I had been thinking about my many families",
        {
            "en-en": 0,
            "pa-en": 1,
            "pa-pa": 2,
            "en-pa": 3
        },
        {
            "form": "past",
            "continuous": true,
            "perfect": true,
            "plural": false,
            "fem": 1,
            "mas": 1
        },
        {
            "pron": "i",
            "verb": "have",
            "noun": "day",
            "det": "the",
            "adj": "first"
        }
    ],
    [
        "I had been thinking about each family",
        "maiṁ harēka parivāra bārē sōcadā rihā sī",
        "ਮੈਂ ਹਰੇਕ ਪਰਿਵਾਰ ਬਾਰੇ ਸੋਚਦਾ ਰਿਹਾ ਸੀ",
        "I had been thinking about each family",
        {
            "en-en": 0,
            "pa-en": 1,
            "pa-pa": 2,
            "en-pa": 3
        },
        {
            "form": "past",
            "continuous": true,
            "perfect": true,
            "plural": false,
            "fem": 1,
            "mas": 1
        },
        {
            "pron": "i",
            "verb": "have",
            "noun": "day",
            "det": "a",
            "adj": "many"
        }
    ],
    [
        "I had been thinking about the first group",
        "maiṁ pahilē samūha bārē sōcadā rihā sī",
        "ਮੈਂ ਪਹਿਲੇ ਸਮੂਹ ਬਾਰੇ ਸੋਚਦਾ ਰਿਹਾ ਸੀ",
        "I had been thinking about the first group",
        {
            "en-en": 0,
            "pa-en": 1,
            "pa-pa": 2,
            "en-pa": 3
        },
        {
            "form": "past",
            "continuous": true,
            "perfect": true,
            "plural": false,
            "fem": 1,
            "mas": 1
        },
        {
            "pron": "i",
            "verb": "have",
            "noun": "day",
            "adj": "each"
        }
    ],
    [
        "I had been thinking about the first home",
        "maiṁ pahilē ghara bārē sōca rihā sī",
        "ਮੈਂ ਪਹਿਲੇ ਘਰ ਬਾਰੇ ਸੋਚ ਰਿਹਾ ਸੀ",
        "I had been thinking about the first home",
        {
            "en-en": 0,
            "pa-en": 1,
            "pa-pa": 2,
            "en-pa": 3
        },
        {
            "form": "past",
            "continuous": true,
            "perfect": true,
            "plural": false,
            "fem": 1,
            "mas": 1
        },
        {
            "pron": "i",
            "verb": "have",
            "noun": "family",
            "det": "the",
            "adj": "first"
        }
    ],
    [
        "I had been thinking about many home",
        "maiṁ bahuta sārē ghara bārē sōcadā rihā sī",
        "ਮੈਂ ਬਹੁਤ ਸਾਰੇ ਘਰ ਬਾਰੇ ਸੋਚਦਾ ਰਿਹਾ ਸੀ",
        "I had been thinking about many home",
        {
            "en-en": 0,
            "pa-en": 1,
            "pa-pa": 2,
            "en-pa": 3
        },
        {
            "form": "past",
            "continuous": true,
            "perfect": true,
            "plural": false,
            "fem": 1,
            "mas": 1
        },
        {
            "pron": "i",
            "verb": "have",
            "noun": "family",
            "det": "my",
            "adj": "many"
        }
    ],
    [
        "I had been thinking about each home",
        "maiṁ hara ghara bārē sōcadā rihā sī",
        "ਮੈਂ ਹਰ ਘਰ ਬਾਰੇ ਸੋਚਦਾ ਰਿਹਾ ਸੀ",
        "I had been thinking about each home",
        {
            "en-en": 0,
            "pa-en": 1,
            "pa-pa": 2,
            "en-pa": 3
        },
        {
            "form": "past",
            "continuous": true,
            "perfect": true,
            "plural": false,
            "fem": 1,
            "mas": 1
        },
        {
            "pron": "i",
            "verb": "have",
            "noun": "family",
            "adj": "each"
        }
    ],
    [
        "I had been thinking about the first job",
        "maiṁ pahilī naukarī bārē sōca rihā sī",
        "ਮੈਂ ਪਹਿਲੀ ਨੌਕਰੀ ਬਾਰੇ ਸੋਚ ਰਿਹਾ ਸੀ",
        "I had been thinking about the first job",
        {
            "en-en": 0,
            "pa-en": 1,
            "pa-pa": 2,
            "en-pa": 3
        },
        {
            "form": "past",
            "continuous": true,
            "perfect": true,
            "plural": false,
            "fem": 1,
            "mas": 1
        },
        {
            "pron": "i",
            "verb": "have",
            "noun": "group",
            "det": "the",
            "adj": "first"
        }
    ],
    [
        "I had been thinking about a many jobs",
        "maiṁ bahuta sārī'āṁ naukarī'āṁ bārē sōca rihā sī",
        "ਮੈਂ ਬਹੁਤ ਸਾਰੀਆਂ ਨੌਕਰੀਆਂ ਬਾਰੇ ਸੋਚ ਰਿਹਾ ਸੀ",
        "I had been thinking about a many jobs",
        {
            "en-en": 0,
            "pa-en": 1,
            "pa-pa": 2,
            "en-pa": 3
        },
        {
            "form": "past",
            "continuous": true,
            "perfect": true,
            "plural": false,
            "fem": 1,
            "mas": 1
        },
        {
            "pron": "i",
            "verb": "have",
            "noun": "group",
            "det": "the",
            "adj": "many"
        }
    ],
    [
        "I had been thinking about each job",
        "maiṁ hara kama bārē sōcadā rihā sī",
        "ਮੈਂ ਹਰ ਕੰਮ ਬਾਰੇ ਸੋਚਦਾ ਰਿਹਾ ਸੀ",
        "I had been thinking about each job",
        {
            "en-en": 0,
            "pa-en": 1,
            "pa-pa": 2,
            "en-pa": 3
        },
        {
            "form": "past",
            "continuous": true,
            "perfect": true,
            "plural": false,
            "fem": 1,
            "mas": 1
        },
        {
            "pron": "i",
            "verb": "have",
            "noun": "group",
            "adj": "each"
        }
    ],
    [
        "I had been thinking about the first mother",
        "maiṁ pahilī māṁ bārē sōca rihā sī",
        "ਮੈਂ ਪਹਿਲੀ ਮਾਂ ਬਾਰੇ ਸੋਚ ਰਿਹਾ ਸੀ",
        "I had been thinking about the first mother",
        {
            "en-en": 0,
            "pa-en": 1,
            "pa-pa": 2,
            "en-pa": 3
        },
        {
            "form": "past",
            "continuous": true,
            "perfect": true,
            "plural": false,
            "fem": 1,
            "mas": 1
        },
        {
            "pron": "i",
            "verb": "have",
            "noun": "job",
            "det": "the",
            "adj": "first"
        }
    ],
    [
        "I had been thinking about my many mothers",
        "maiṁ āpaṇī'āṁ bahuta sārī'āṁ māvāṁ bārē sōcadā rihā sī",
        "ਮੈਂ ਆਪਣੀਆਂ ਬਹੁਤ ਸਾਰੀਆਂ ਮਾਵਾਂ ਬਾਰੇ ਸੋਚਦਾ ਰਿਹਾ ਸੀ",
        "I had been thinking about my many mothers",
        {
            "en-en": 0,
            "pa-en": 1,
            "pa-pa": 2,
            "en-pa": 3
        },
        {
            "form": "past",
            "continuous": true,
            "perfect": true,
            "plural": false,
            "fem": 1,
            "mas": 1
        },
        {
            "pron": "i",
            "verb": "have",
            "noun": "job",
            "det": "a",
            "adj": "many"
        }
    ],
    [
        "I had been thinking about each mother",
        "maiṁ hara māṁ bārē sōcadā rihā sī",
        "ਮੈਂ ਹਰ ਮਾਂ ਬਾਰੇ ਸੋਚਦਾ ਰਿਹਾ ਸੀ",
        "I had been thinking about each mother",
        {
            "en-en": 0,
            "pa-en": 1,
            "pa-pa": 2,
            "en-pa": 3
        },
        {
            "form": "past",
            "continuous": true,
            "perfect": true,
            "plural": false,
            "fem": 1,
            "mas": 1
        },
        {
            "pron": "i",
            "verb": "have",
            "noun": "job",
            "adj": "each"
        }
    ],
    [
        "I had been thinking about a many problems",
        "maiṁ bahuta sārī'āṁ muśakalāṁ bārē sōcadā rihā sī",
        "ਮੈਂ ਬਹੁਤ ਸਾਰੀਆਂ ਮੁਸ਼ਕਲਾਂ ਬਾਰੇ ਸੋਚਦਾ ਰਿਹਾ ਸੀ",
        "I had been thinking about a many problems",
        {
            "en-en": 0,
            "pa-en": 1,
            "pa-pa": 2,
            "en-pa": 3
        },
        {
            "form": "past",
            "continuous": true,
            "perfect": true,
            "plural": false,
            "fem": 1,
            "mas": 1
        },
        {
            "pron": "i",
            "verb": "have",
            "noun": "mother",
            "det": "the",
            "adj": "first"
        }
    ],
    [
        "I had been thinking about each problem",
        "maiṁ hara samasi'ā bārē sōcadā rihā sī",
        "ਮੈਂ ਹਰ ਸਮੱਸਿਆ ਬਾਰੇ ਸੋਚਦਾ ਰਿਹਾ ਸੀ",
        "I had been thinking about each problem",
        {
            "en-en": 0,
            "pa-en": 1,
            "pa-pa": 2,
            "en-pa": 3
        },
        {
            "form": "past",
            "continuous": true,
            "perfect": true,
            "plural": false,
            "fem": 1,
            "mas": 1
        },
        {
            "pron": "i",
            "verb": "have",
            "noun": "mother",
            "det": "my",
            "adj": "many"
        }
    ],
    [
        "I had been thinking about a good question",
        "maiṁ ika cagē praśana bārē sōca rihā sī",
        "ਮੈਂ ਇੱਕ ਚੰਗੇ ਪ੍ਰਸ਼ਨ ਬਾਰੇ ਸੋਚ ਰਿਹਾ ਸੀ",
        "I had been thinking about a good question",
        {
            "en-en": 0,
            "pa-en": 1,
            "pa-pa": 2,
            "en-pa": 3
        },
        {
            "form": "past",
            "continuous": true,
            "perfect": true,
            "plural": false,
            "fem": 1,
            "mas": 1
        },
        {
            "pron": "i",
            "verb": "have",
            "noun": "mother",
            "adj": "each"
        }
    ],
    [
        "I had been thinking about the first work",
        "maiṁ pahilē kama bārē sōcadā rihā sī",
        "ਮੈਂ ਪਹਿਲੇ ਕੰਮ ਬਾਰੇ ਸੋਚਦਾ ਰਿਹਾ ਸੀ",
        "I had been thinking about the first work",
        {
            "en-en": 0,
            "pa-en": 1,
            "pa-pa": 2,
            "en-pa": 3
        },
        {
            "form": "past",
            "continuous": true,
            "perfect": true,
            "plural": false,
            "fem": 1,
            "mas": 1
        },
        {
            "pron": "i",
            "verb": "have",
            "noun": "right",
            "det": "the",
            "adj": "first"
        }
    ],
    [
        "I had been thinking about each work",
        "maiṁ hara kama bārē sōcadā rihā sī",
        "ਮੈਂ ਹਰ ਕੰਮ ਬਾਰੇ ਸੋਚਦਾ ਰਿਹਾ ਸੀ",
        "I had been thinking about each work",
        {
            "en-en": 0,
            "pa-en": 1,
            "pa-pa": 2,
            "en-pa": 3
        },
        {
            "form": "past",
            "continuous": true,
            "perfect": true,
            "plural": false,
            "fem": 1,
            "mas": 1
        },
        {
            "pron": "i",
            "verb": "have",
            "noun": "right",
            "adj": "many"
        }
    ],
    [
        "I had been thinking about the first world",
        "maiṁ pahilē sasāra bārē sōca rihā sī",
        "ਮੈਂ ਪਹਿਲੇ ਸੰਸਾਰ ਬਾਰੇ ਸੋਚ ਰਿਹਾ ਸੀ",
        "I had been thinking about the first world",
        {
            "en-en": 0,
            "pa-en": 1,
            "pa-pa": 2,
            "en-pa": 3
        },
        {
            "form": "past",
            "continuous": true,
            "perfect": true,
            "plural": false,
            "fem": 1,
            "mas": 1
        },
        {
            "pron": "i",
            "verb": "have",
            "noun": "right",
            "adj": "each"
        }
    ],
    [
        "I had been thinking about the many worlds",
        "maiṁ bahuta sārē sasārāṁ bārē sōcadā rihā sī",
        "ਮੈਂ ਬਹੁਤ ਸਾਰੇ ਸੰਸਾਰਾਂ ਬਾਰੇ ਸੋਚਦਾ ਰਿਹਾ ਸੀ",
        "I had been thinking about the many worlds",
        {
            "en-en": 0,
            "pa-en": 1,
            "pa-pa": 2,
            "en-pa": 3
        },
        {
            "form": "past",
            "continuous": true,
            "perfect": true,
            "plural": false,
            "fem": 1,
            "mas": 1
        },
        {
            "pron": "i",
            "verb": "have",
            "noun": "room",
            "det": "the",
            "adj": "first"
        }
    ],
    [
        "I had been thinking about each world",
        "Maiṁ hara ika sasāra bārē sōcadā rihā sī",
        "ਮੈਂ ਹਰ ਇਕ ਸੰਸਾਰ ਬਾਰੇ ਸੋਚਦਾ ਰਿਹਾ ਸੀ",
        "I had been thinking about each world",
        {
            "en-en": 0,
            "pa-en": 1,
            "pa-pa": 2,
            "en-pa": 3
        },
        {
            "form": "past",
            "continuous": true,
            "perfect": true,
            "plural": false,
            "fem": 1,
            "mas": 1
        },
        {
            "pron": "i",
            "verb": "have",
            "noun": "room",
            "det": "a",
            "adj": "many"
        }
    ],
    [
        "I had been looking at a good book",
        "maiṁ ika cagī kitāba vala vēkha rihā sī",
        "ਮੈਂ ਇਕ ਚੰਗੀ ਕਿਤਾਬ ਵੱਲ ਵੇਖ ਰਿਹਾ ਸੀ",
        "I had been looking at a good book",
        {
            "en-en": 0,
            "pa-en": 1,
            "pa-pa": 2,
            "en-pa": 3
        },
        {
            "form": "past",
            "continuous": true,
            "perfect": true,
            "plural": false,
            "fem": 1,
            "mas": 1
        },
        {
            "pron": "i",
            "verb": "have",
            "noun": "room",
            "adj": "each"
        }
    ],
    [
        "I had been looking after the first child",
        "maiṁ pahilē bacē dī dēkhabhāla kara rihā sī",
        "ਮੈਂ ਪਹਿਲੇ ਬੱਚੇ ਦੀ ਦੇਖਭਾਲ ਕਰ ਰਿਹਾ ਸੀ",
        "I had been looking after the first child",
        {
            "en-en": 0,
            "pa-en": 1,
            "pa-pa": 2,
            "en-pa": 3
        },
        {
            "form": "past",
            "continuous": true,
            "perfect": true,
            "plural": false,
            "fem": 1,
            "mas": 1
        },
        {
            "pron": "i",
            "verb": "have",
            "noun": "story",
            "det": "a",
            "adj": "good"
        }
    ],
    [
        "I had been looking after my many children",
        "maiṁ āpaṇē bahuta sārē baci'āṁ dī dēkhabhāla kara rihā sī",
        "ਮੈਂ ਆਪਣੇ ਬਹੁਤ ਸਾਰੇ ਬੱਚਿਆਂ ਦੀ ਦੇਖਭਾਲ ਕਰ ਰਿਹਾ ਸੀ",
        "I had been looking after my many children",
        {
            "en-en": 0,
            "pa-en": 1,
            "pa-pa": 2,
            "en-pa": 3
        },
        {
            "form": "past",
            "continuous": true,
            "perfect": true,
            "plural": false,
            "fem": 1,
            "mas": 1
        },
        {
            "pron": "i",
            "verb": "have",
            "noun": "story",
            "det": "the",
            "adj": "first"
        }
    ],
    [
        "I had been looking after each child",
        "maiṁ hara bacē dī dēkhabhāla kara rihā sī",
        "ਮੈਂ ਹਰ ਬੱਚੇ ਦੀ ਦੇਖਭਾਲ ਕਰ ਰਿਹਾ ਸੀ",
        "I had been looking after each child",
        {
            "en-en": 0,
            "pa-en": 1,
            "pa-pa": 2,
            "en-pa": 3
        },
        {
            "form": "past",
            "continuous": true,
            "perfect": true,
            "plural": false,
            "fem": 1,
            "mas": 1
        },
        {
            "pron": "i",
            "verb": "have",
            "noun": "story",
            "det": "a",
            "adj": "many"
        }
    ],
    [
        "I had been looking after the first family",
        "maiṁ pahilē parivāra dī dēkhabhāla kara rihā sī",
        "ਮੈਂ ਪਹਿਲੇ ਪਰਿਵਾਰ ਦੀ ਦੇਖਭਾਲ ਕਰ ਰਿਹਾ ਸੀ",
        "I had been looking after the first family",
        {
            "en-en": 0,
            "pa-en": 1,
            "pa-pa": 2,
            "en-pa": 3
        },
        {
            "form": "past",
            "continuous": true,
            "perfect": true,
            "plural": false,
            "fem": 1,
            "mas": 1
        },
        {
            "pron": "i",
            "verb": "have",
            "noun": "story",
            "adj": "each"
        }
    ],
    [
        "I had been looking at a many men",
        "maiṁ bahuta sārē badi'āṁ nū vēkha rihā sī",
        "ਮੈਂ ਬਹੁਤ ਸਾਰੇ ਬੰਦਿਆਂ ਨੂੰ ਵੇਖ ਰਿਹਾ ਸੀ",
        "I had been looking at a many men",
        {
            "en-en": 0,
            "pa-en": 1,
            "pa-pa": 2,
            "en-pa": 3
        },
        {
            "form": "past",
            "continuous": true,
            "perfect": true,
            "plural": false,
            "fem": 1,
            "mas": 1
        },
        {
            "pron": "i",
            "verb": "have",
            "noun": "thing",
            "det": "a",
            "adj": "good"
        }
    ],
    [
        "I had been looking at each man",
        "maiṁ harēka ādamī vala vēkha rihā sī",
        "ਮੈਂ ਹਰੇਕ ਆਦਮੀ ਵੱਲ ਵੇਖ ਰਿਹਾ ਸੀ",
        "I had been looking at each man",
        {
            "en-en": 0,
            "pa-en": 1,
            "pa-pa": 2,
            "en-pa": 3
        },
        {
            "form": "past",
            "continuous": true,
            "perfect": true,
            "plural": false,
            "fem": 1,
            "mas": 1
        },
        {
            "pron": "i",
            "verb": "have",
            "noun": "thing",
            "det": "the",
            "adj": "first"
        }
    ],
    [
        "I had been looking after the first mother",
        "maiṁ pahilī māṁ dī dēkhabhāla kara rihā sī",
        "ਮੈਂ ਪਹਿਲੀ ਮਾਂ ਦੀ ਦੇਖਭਾਲ ਕਰ ਰਿਹਾ ਸੀ",
        "I had been looking after the first mother",
        {
            "en-en": 0,
            "pa-en": 1,
            "pa-pa": 2,
            "en-pa": 3
        },
        {
            "form": "past",
            "continuous": true,
            "perfect": true,
            "plural": false,
            "fem": 1,
            "mas": 1
        },
        {
            "pron": "i",
            "verb": "have",
            "noun": "thing",
            "det": "a",
            "adj": "many"
        }
    ],
    [
        "I had been looking after my many mothers",
        "maiṁ āpaṇī'āṁ bahuta sārī'āṁ māvāṁ dī dēkhabhāla kara rihā sī",
        "ਮੈਂ ਆਪਣੀਆਂ ਬਹੁਤ ਸਾਰੀਆਂ ਮਾਵਾਂ ਦੀ ਦੇਖਭਾਲ ਕਰ ਰਿਹਾ ਸੀ",
        "I had been looking after my many mothers",
        {
            "en-en": 0,
            "pa-en": 1,
            "pa-pa": 2,
            "en-pa": 3
        },
        {
            "form": "past",
            "continuous": true,
            "perfect": true,
            "plural": false,
            "fem": 1,
            "mas": 1
        },
        {
            "pron": "i",
            "verb": "have",
            "noun": "thing",
            "adj": "each"
        }
    ],
    [
        "I had been looking for each work",
        "maiṁ hara kama dī bhāla vica sī",
        "ਮੈਂ ਹਰ ਕੰਮ ਦੀ ਭਾਲ ਵਿਚ ਸੀ",
        "I had been looking for each work",
        {
            "en-en": 0,
            "pa-en": 1,
            "pa-pa": 2,
            "en-pa": 3
        },
        {
            "form": "past",
            "continuous": true,
            "perfect": true,
            "plural": false,
            "fem": 1,
            "mas": 1
        },
        {
            "pron": "i",
            "verb": "have",
            "noun": "work",
            "adj": "good"
        }
    ],
    [
        "I had been looking at the first world",
        "maiṁ pahilē sasāra nū vēkha rihā sī",
        "ਮੈਂ ਪਹਿਲੇ ਸੰਸਾਰ ਨੂੰ ਵੇਖ ਰਿਹਾ ਸੀ",
        "I had been looking at the first world",
        {
            "en-en": 0,
            "pa-en": 1,
            "pa-pa": 2,
            "en-pa": 3
        },
        {
            "form": "past",
            "continuous": true,
            "perfect": true,
            "plural": false,
            "fem": 1,
            "mas": 1
        },
        {
            "pron": "i",
            "verb": "have",
            "noun": "work",
            "det": "the",
            "adj": "first"
        }
    ],
    [
        "I had been looking at the many worlds",
        "Maiṁ bahuta sārē sasārāṁ vala vēkha rihā sī",
        "ਮੈਂ ਬਹੁਤ ਸਾਰੇ ਸੰਸਾਰਾਂ ਵੱਲ ਵੇਖ ਰਿਹਾ ਸੀ",
        "I had been looking at the many worlds",
        {
            "en-en": 0,
            "pa-en": 1,
            "pa-pa": 2,
            "en-pa": 3
        },
        {
            "form": "past",
            "continuous": true,
            "perfect": true,
            "plural": false,
            "fem": 1,
            "mas": 1
        },
        {
            "pron": "i",
            "verb": "have",
            "noun": "work",
            "adj": "each"
        }
    ],
    [
        "I had been looking at each world",
        "maiṁ hara ika sasāra nū vēkha rihā sī",
        "ਮੈਂ ਹਰ ਇਕ ਸੰਸਾਰ ਨੂੰ ਵੇਖ ਰਿਹਾ ਸੀ",
        "I had been looking at each world",
        {
            "en-en": 0,
            "pa-en": 1,
            "pa-pa": 2,
            "en-pa": 3
        },
        {
            "form": "past",
            "continuous": true,
            "perfect": true,
            "plural": false,
            "fem": 1,
            "mas": 1
        },
        {
            "pron": "i",
            "verb": "do",
            "noun": "business",
            "det": "a",
            "adj": "good"
        }
    ],
    [
        "I had been wanting a good book",
        "maiṁ ika cagī kitāba dī maga kara rihā sī",
        "ਮੈਂ ਇੱਕ ਚੰਗੀ ਕਿਤਾਬ ਦੀ ਮੰਗ ਕਰ ਰਿਹਾ ਸੀ",
        "I had been wanting a good book",
        {
            "en-en": 0,
            "pa-en": 1,
            "pa-pa": 2,
            "en-pa": 3
        },
        {
            "form": "past",
            "continuous": true,
            "perfect": true,
            "plural": false,
            "fem": 1,
            "mas": 1
        },
        {
            "pron": "i",
            "verb": "do",
            "noun": "business",
            "adj": "each"
        }
    ],
    [
        "I had been wanting each book",
        "maiṁ hara kitāba cāhudā sī",
        "ਮੈਂ ਹਰ ਕਿਤਾਬ ਚਾਹੁੰਦਾ ਸੀ",
        "I had been wanting each book",
        {
            "en-en": 0,
            "pa-en": 1,
            "pa-pa": 2,
            "en-pa": 3
        },
        {
            "form": "past",
            "continuous": true,
            "perfect": true,
            "plural": false,
            "fem": 1,
            "mas": 1
        },
        {
            "pron": "i",
            "verb": "do",
            "noun": "job",
            "det": "the",
            "adj": "first"
        }
    ],
    [
        "I had been wanting a good day",
        "maiṁ ika cagā dina cāhudā sī",
        "ਮੈਂ ਇੱਕ ਚੰਗਾ ਦਿਨ ਚਾਹੁੰਦਾ ਸੀ",
        "I had been wanting a good day",
        {
            "en-en": 0,
            "pa-en": 1,
            "pa-pa": 2,
            "en-pa": 3
        },
        {
            "form": "past",
            "continuous": true,
            "perfect": true,
            "plural": false,
            "fem": 1,
            "mas": 1
        },
        {
            "pron": "i",
            "verb": "do",
            "noun": "job",
            "det": "a",
            "adj": "many"
        }
    ],
    [
        "I had been wanting the first day",
        "maiṁ pahilē dina dī cāhata kītī sī",
        "ਮੈਂ ਪਹਿਲੇ ਦਿਨ ਦੀ ਚਾਹਤ ਕੀਤੀ ਸੀ",
        "I had been wanting the first day",
        {
            "en-en": 0,
            "pa-en": 1,
            "pa-pa": 2,
            "en-pa": 3
        },
        {
            "form": "past",
            "continuous": true,
            "perfect": true,
            "plural": false,
            "fem": 1,
            "mas": 1
        },
        {
            "pron": "i",
            "verb": "do",
            "noun": "job",
            "adj": "each"
        }
    ],
    [
        "I had been wanting each group",
        "maiṁ hara samūha nū cāhudā sī",
        "ਮੈਂ ਹਰ ਸਮੂਹ ਨੂੰ ਚਾਹੁੰਦਾ ਸੀ",
        "I had been wanting each group",
        {
            "en-en": 0,
            "pa-en": 1,
            "pa-pa": 2,
            "en-pa": 3
        },
        {
            "form": "past",
            "continuous": true,
            "perfect": true,
            "plural": false,
            "fem": 1,
            "mas": 1
        },
        {
            "pron": "i",
            "verb": "do",
            "noun": "right",
            "det": "the",
            "adj": "first"
        }
    ],
    [
        "I had been wanting a first home",
        "maiṁ pahilā ghara cāhudā sī",
        "ਮੈਂ ਪਹਿਲਾ ਘਰ ਚਾਹੁੰਦਾ ਸੀ",
        "I had been wanting a first home",
        {
            "en-en": 0,
            "pa-en": 1,
            "pa-pa": 2,
            "en-pa": 3
        },
        {
            "form": "past",
            "continuous": true,
            "perfect": true,
            "plural": false,
            "fem": 1,
            "mas": 1
        },
        {
            "pron": "i",
            "verb": "do",
            "noun": "right",
            "adj": "many"
        }
    ],
    [
        "I had been wanting a many home",
        "maiṁ bahuta sārā ghara cāhudā sī",
        "ਮੈਂ ਬਹੁਤ ਸਾਰਾ ਘਰ ਚਾਹੁੰਦਾ ਸੀ",
        "I had been wanting a many home",
        {
            "en-en": 0,
            "pa-en": 1,
            "pa-pa": 2,
            "en-pa": 3
        },
        {
            "form": "past",
            "continuous": true,
            "perfect": true,
            "plural": false,
            "fem": 1,
            "mas": 1
        },
        {
            "pron": "i",
            "verb": "do",
            "noun": "right",
            "adj": "each"
        }
    ],
    [
        "I had been wanting a home",
        "mainū ika ghara cāhīdā sī",
        "ਮੈਨੂੰ ਇੱਕ ਘਰ ਚਾਹੀਦਾ ਸੀ",
        "I had been wanting a home",
        {
            "en-en": 0,
            "pa-en": 1,
            "pa-pa": 2,
            "en-pa": 3
        },
        {
            "form": "past",
            "continuous": true,
            "perfect": true,
            "plural": false,
            "fem": 1,
            "mas": 1
        },
        {
            "pron": "i",
            "verb": "do",
            "noun": "thing",
            "det": "a",
            "adj": "good"
        }
    ],
    [
        "I had been wanting the first job",
        "maiṁ pahilī naukarī cāhudā sī",
        "ਮੈਂ ਪਹਿਲੀ ਨੌਕਰੀ ਚਾਹੁੰਦਾ ਸੀ",
        "I had been wanting the first job",
        {
            "en-en": 0,
            "pa-en": 1,
            "pa-pa": 2,
            "en-pa": 3
        },
        {
            "form": "past",
            "continuous": true,
            "perfect": true,
            "plural": false,
            "fem": 1,
            "mas": 1
        },
        {
            "pron": "i",
            "verb": "do",
            "noun": "thing",
            "det": "the",
            "adj": "first"
        }
    ],
    [
        "I had been wanting a many jobs",
        "maiṁ bahuta sārī'āṁ naukarī'āṁ cāhudā sī",
        "ਮੈਂ ਬਹੁਤ ਸਾਰੀਆਂ ਨੌਕਰੀਆਂ ਚਾਹੁੰਦਾ ਸੀ",
        "I had been wanting a many jobs",
        {
            "en-en": 0,
            "pa-en": 1,
            "pa-pa": 2,
            "en-pa": 3
        },
        {
            "form": "past",
            "continuous": true,
            "perfect": true,
            "plural": false,
            "fem": 1,
            "mas": 1
        },
        {
            "pron": "i",
            "verb": "do",
            "noun": "thing",
            "det": "a",
            "adj": "many"
        }
    ],
    [
        "I had been wanting each job",
        "maiṁ hara naukarī cāhudā sī",
        "ਮੈਂ ਹਰ ਨੌਕਰੀ ਚਾਹੁੰਦਾ ਸੀ",
        "I had been wanting each job",
        {
            "en-en": 0,
            "pa-en": 1,
            "pa-pa": 2,
            "en-pa": 3
        },
        {
            "form": "past",
            "continuous": true,
            "perfect": true,
            "plural": false,
            "fem": 1,
            "mas": 1
        },
        {
            "pron": "i",
            "verb": "do",
            "noun": "thing",
            "adj": "each"
        }
    ],
    [
        "I had been wanting the first place",
        "maiṁ pahilē sathāna dī cāhata rihā sī",
        "ਮੈਂ ਪਹਿਲੇ ਸਥਾਨ ਦੀ ਚਾਹਤ ਰਿਹਾ ਸੀ",
        "I had been wanting the first place",
        {
            "en-en": 0,
            "pa-en": 1,
            "pa-pa": 2,
            "en-pa": 3
        },
        {
            "form": "past",
            "continuous": true,
            "perfect": true,
            "plural": false,
            "fem": 1,
            "mas": 1
        },
        {
            "pron": "i",
            "verb": "do",
            "noun": "work",
            "adj": "good"
        }
    ],
    [
        "I had been wanting a many places",
        "mainū bahuta sārī'āṁ thāvāṁ cāhīdī'āṁ sana",
        "ਮੈਨੂੰ ਬਹੁਤ ਸਾਰੀਆਂ ਥਾਵਾਂ ਚਾਹੀਦੀਆਂ ਸਨ",
        "I had been wanting a many places",
        {
            "en-en": 0,
            "pa-en": 1,
            "pa-pa": 2,
            "en-pa": 3
        },
        {
            "form": "past",
            "continuous": true,
            "perfect": true,
            "plural": false,
            "fem": 1,
            "mas": 1
        },
        {
            "pron": "i",
            "verb": "do",
            "noun": "work",
            "det": "the",
            "adj": "first"
        }
    ],
    [
        "I had been wanting each place",
        "maiṁ hara jag'hā cāhudā sī",
        "ਮੈਂ ਹਰ ਜਗ੍ਹਾ ਚਾਹੁੰਦਾ ਸੀ",
        "I had been wanting each place",
        {
            "en-en": 0,
            "pa-en": 1,
            "pa-pa": 2,
            "en-pa": 3
        },
        {
            "form": "past",
            "continuous": true,
            "perfect": true,
            "plural": false,
            "fem": 1,
            "mas": 1
        },
        {
            "pron": "i",
            "verb": "do",
            "noun": "work",
            "adj": "each"
        }
    ],
    [
        "I had known each student",
        "maiṁ harēka vidi'ārathī nū jāṇadā sī",
        "ਮੈਂ ਹਰੇਕ ਵਿਦਿਆਰਥੀ ਨੂੰ ਜਾਣਦਾ ਸੀ",
        "I had known each student",
        {
            "en-en": 0,
            "pa-en": 1,
            "pa-pa": 2,
            "en-pa": 3
        },
        {
            "form": "past",
            "continuous": true,
            "perfect": true,
            "plural": false,
            "fem": 1,
            "mas": 1
        },
        {
            "pron": "i",
            "verb": "think",
            "noun": "business",
            "det": "a",
            "adj": "good"
        }
    ],
    [
        "I had known a good system",
        "mainū ika cagā sisaṭama patā sī",
        "ਮੈਨੂੰ ਇੱਕ ਚੰਗਾ ਸਿਸਟਮ ਪਤਾ ਸੀ",
        "I had known a good system",
        {
            "en-en": 0,
            "pa-en": 1,
            "pa-pa": 2,
            "en-pa": 3
        },
        {
            "form": "past",
            "continuous": true,
            "perfect": true,
            "plural": false,
            "fem": 1,
            "mas": 1
        },
        {
            "pron": "i",
            "verb": "think",
            "noun": "business",
            "adj": "each"
        }
    ],
    [
        "I had known by many things",
        "maiṁ bahuta sārī'āṁ cīzāṁ du'ārā jāṇi'ā sī",
        "ਮੈਂ ਬਹੁਤ ਸਾਰੀਆਂ ਚੀਜ਼ਾਂ ਦੁਆਰਾ ਜਾਣਿਆ ਸੀ",
        "I had known by many things",
        {
            "en-en": 0,
            "pa-en": 1,
            "pa-pa": 2,
            "en-pa": 3
        },
        {
            "form": "past",
            "continuous": true,
            "perfect": true,
            "plural": false,
            "fem": 1,
            "mas": 1
        },
        {
            "pron": "i",
            "verb": "think",
            "noun": "family",
            "det": "the",
            "adj": "first"
        }
    ],
    [
        "I had known by each thing",
        "mainū hara cīza du'ārā patā sī",
        "ਮੈਨੂੰ ਹਰ ਚੀਜ਼ ਦੁਆਰਾ ਪਤਾ ਸੀ",
        "I had known by each thing",
        {
            "en-en": 0,
            "pa-en": 1,
            "pa-pa": 2,
            "en-pa": 3
        },
        {
            "form": "past",
            "continuous": true,
            "perfect": true,
            "plural": false,
            "fem": 1,
            "mas": 1
        },
        {
            "pron": "i",
            "verb": "think",
            "noun": "family",
            "det": "my",
            "adj": "many"
        }
    ],
    [
        "I had known my good time",
        "maiṁ āpaṇā cagā samāṁ jāṇadā sī",
        "ਮੈਂ ਆਪਣਾ ਚੰਗਾ ਸਮਾਂ ਜਾਣਦਾ ਸੀ",
        "I had known my good time",
        {
            "en-en": 0,
            "pa-en": 1,
            "pa-pa": 2,
            "en-pa": 3
        },
        {
            "form": "past",
            "continuous": true,
            "perfect": true,
            "plural": false,
            "fem": 1,
            "mas": 1
        },
        {
            "pron": "i",
            "verb": "think",
            "noun": "family",
            "adj": "each"
        }
    ],
    [
        "I had known my first time",
        "mainū mērī pahilī vāra patā sī",
        "ਮੈਨੂੰ ਮੇਰੀ ਪਹਿਲੀ ਵਾਰ ਪਤਾ ਸੀ",
        "I had known my first time",
        {
            "en-en": 0,
            "pa-en": 1,
            "pa-pa": 2,
            "en-pa": 3
        },
        {
            "form": "past",
            "continuous": true,
            "perfect": true,
            "plural": false,
            "fem": 1,
            "mas": 1
        },
        {
            "pron": "i",
            "verb": "think",
            "noun": "group",
            "det": "the",
            "adj": "first"
        }
    ],
    [
        "I had known my many times",
        "mainū mērē bahuta vāra patā sī",
        "ਮੈਨੂੰ ਮੇਰੇ ਬਹੁਤ ਵਾਰ ਪਤਾ ਸੀ",
        "I had known my many times",
        {
            "en-en": 0,
            "pa-en": 1,
            "pa-pa": 2,
            "en-pa": 3
        },
        {
            "form": "past",
            "continuous": true,
            "perfect": true,
            "plural": false,
            "fem": 1,
            "mas": 1
        },
        {
            "pron": "i",
            "verb": "think",
            "noun": "group",
            "det": "the",
            "adj": "many"
        }
    ],
    [
        "I had known by each time",
        "mainū hara vāra patā sī",
        "ਮੈਨੂੰ ਹਰ ਵਾਰ ਪਤਾ ਸੀ",
        "I had known by each time",
        {
            "en-en": 0,
            "pa-en": 1,
            "pa-pa": 2,
            "en-pa": 3
        },
        {
            "form": "past",
            "continuous": true,
            "perfect": true,
            "plural": false,
            "fem": 1,
            "mas": 1
        },
        {
            "pron": "i",
            "verb": "think",
            "noun": "group",
            "adj": "each"
        }
    ],
    [
        "I had known the first woman",
        "maiṁ pahilī knownrata nū jāṇi'ā sī",
        "ਮੈਂ ਪਹਿਲੀ knownਰਤ ਨੂੰ ਜਾਣਿਆ ਸੀ",
        "I had known the first woman",
        {
            "en-en": 0,
            "pa-en": 1,
            "pa-pa": 2,
            "en-pa": 3
        },
        {
            "form": "past",
            "continuous": true,
            "perfect": true,
            "plural": false,
            "fem": 1,
            "mas": 1
        },
        {
            "pron": "i",
            "verb": "think",
            "noun": "job",
            "det": "the",
            "adj": "first"
        }
    ],
    [
        "I had known a many women",
        "maiṁ bahuta sārī'āṁ.Ratāṁ nū jāṇadā sī",
        "ਮੈਂ ਬਹੁਤ ਸਾਰੀਆਂ .ਰਤਾਂ ਨੂੰ ਜਾਣਦਾ ਸੀ",
        "I had known a many women",
        {
            "en-en": 0,
            "pa-en": 1,
            "pa-pa": 2,
            "en-pa": 3
        },
        {
            "form": "past",
            "continuous": true,
            "perfect": true,
            "plural": false,
            "fem": 1,
            "mas": 1
        },
        {
            "pron": "i",
            "verb": "think",
            "noun": "job",
            "det": "a",
            "adj": "many"
        }
    ],
    [
        "I had known each woman",
        "maiṁ harēka knownrata nū jāṇadā sī",
        "ਮੈਂ ਹਰੇਕ knownਰਤ ਨੂੰ ਜਾਣਦਾ ਸੀ",
        "I had known each woman",
        {
            "en-en": 0,
            "pa-en": 1,
            "pa-pa": 2,
            "en-pa": 3
        },
        {
            "form": "past",
            "continuous": true,
            "perfect": true,
            "plural": false,
            "fem": 1,
            "mas": 1
        },
        {
            "pron": "i",
            "verb": "think",
            "noun": "job",
            "adj": "each"
        }
    ],
    [
        "I had known my first work",
        "mainū āpaṇā pahilā kama patā sī",
        "ਮੈਨੂੰ ਆਪਣਾ ਪਹਿਲਾ ਕੰਮ ਪਤਾ ਸੀ",
        "I had known my first work",
        {
            "en-en": 0,
            "pa-en": 1,
            "pa-pa": 2,
            "en-pa": 3
        },
        {
            "form": "past",
            "continuous": true,
            "perfect": true,
            "plural": false,
            "fem": 1,
            "mas": 1
        },
        {
            "pron": "i",
            "verb": "think",
            "noun": "mother",
            "det": "the",
            "adj": "first"
        }
    ],
    [
        "I had known by each work",
        "mainū hara kama du'ārā patā sī",
        "ਮੈਨੂੰ ਹਰ ਕੰਮ ਦੁਆਰਾ ਪਤਾ ਸੀ",
        "I had known by each work",
        {
            "en-en": 0,
            "pa-en": 1,
            "pa-pa": 2,
            "en-pa": 3
        },
        {
            "form": "past",
            "continuous": true,
            "perfect": true,
            "plural": false,
            "fem": 1,
            "mas": 1
        },
        {
            "pron": "i",
            "verb": "think",
            "noun": "mother",
            "det": "my",
            "adj": "many"
        }
    ],
    [
        "I had been taking a good book",
        "maiṁ ika cagī kitāba lai rihā sī",
        "ਮੈਂ ਇਕ ਚੰਗੀ ਕਿਤਾਬ ਲੈ ਰਿਹਾ ਸੀ",
        "I had been taking a good book",
        {
            "en-en": 0,
            "pa-en": 1,
            "pa-pa": 2,
            "en-pa": 3
        },
        {
            "form": "past",
            "continuous": true,
            "perfect": true,
            "plural": false,
            "fem": 1,
            "mas": 1
        },
        {
            "pron": "i",
            "verb": "think",
            "noun": "mother",
            "adj": "each"
        }
    ],
    [
        "I had been taking each book",
        "maiṁ hara kitāba lai rihā sī",
        "ਮੈਂ ਹਰ ਕਿਤਾਬ ਲੈ ਰਿਹਾ ਸੀ",
        "I had been taking each book",
        {
            "en-en": 0,
            "pa-en": 1,
            "pa-pa": 2,
            "en-pa": 3
        },
        {
            "form": "past",
            "continuous": true,
            "perfect": true,
            "plural": false,
            "fem": 1,
            "mas": 1
        },
        {
            "pron": "i",
            "verb": "think",
            "noun": "people",
            "det": "the",
            "adj": "first"
        }
    ],
    [
        "I had been taking a good day",
        "maiṁ ika cagā dina bitā rihā sī",
        "ਮੈਂ ਇੱਕ ਚੰਗਾ ਦਿਨ ਬਿਤਾ ਰਿਹਾ ਸੀ",
        "I had been taking a good day",
        {
            "en-en": 0,
            "pa-en": 1,
            "pa-pa": 2,
            "en-pa": 3
        },
        {
            "form": "past",
            "continuous": true,
            "perfect": true,
            "plural": false,
            "fem": 1,
            "mas": 1
        },
        {
            "pron": "i",
            "verb": "think",
            "noun": "people",
            "adj": "many"
        }
    ],
    [
        "I had been taking a many jobs",
        "maiṁ bahuta sārī'āṁ naukarī'āṁ laindā rihā sī",
        "ਮੈਂ ਬਹੁਤ ਸਾਰੀਆਂ ਨੌਕਰੀਆਂ ਲੈਂਦਾ ਰਿਹਾ ਸੀ",
        "I had been taking a many jobs",
        {
            "en-en": 0,
            "pa-en": 1,
            "pa-pa": 2,
            "en-pa": 3
        },
        {
            "form": "past",
            "continuous": true,
            "perfect": true,
            "plural": false,
            "fem": 1,
            "mas": 1
        },
        {
            "pron": "i",
            "verb": "think",
            "noun": "right",
            "det": "the",
            "adj": "first"
        }
    ],
    [
        "I had been taking each job",
        "maiṁ hara naukarī kara rihā sī",
        "ਮੈਂ ਹਰ ਨੌਕਰੀ ਕਰ ਰਿਹਾ ਸੀ",
        "I had been taking each job",
        {
            "en-en": 0,
            "pa-en": 1,
            "pa-pa": 2,
            "en-pa": 3
        },
        {
            "form": "past",
            "continuous": true,
            "perfect": true,
            "plural": false,
            "fem": 1,
            "mas": 1
        },
        {
            "pron": "i",
            "verb": "think",
            "noun": "right",
            "adj": "many"
        }
    ],
    [
        "I had been taking a good point",
        "maiṁ ika cagī gala lai rihā sī",
        "ਮੈਂ ਇਕ ਚੰਗੀ ਗੱਲ ਲੈ ਰਿਹਾ ਸੀ",
        "I had been taking a good point",
        {
            "en-en": 0,
            "pa-en": 1,
            "pa-pa": 2,
            "en-pa": 3
        },
        {
            "form": "past",
            "continuous": true,
            "perfect": true,
            "plural": false,
            "fem": 1,
            "mas": 1
        },
        {
            "pron": "i",
            "verb": "think",
            "noun": "right",
            "adj": "each"
        }
    ],
    [
        "I had been taking a good thing",
        "maiṁ cagī cīza lai rihā sī",
        "ਮੈਂ ਚੰਗੀ ਚੀਜ਼ ਲੈ ਰਿਹਾ ਸੀ",
        "I had been taking a good thing",
        {
            "en-en": 0,
            "pa-en": 1,
            "pa-pa": 2,
            "en-pa": 3
        },
        {
            "form": "past",
            "continuous": true,
            "perfect": true,
            "plural": false,
            "fem": 1,
            "mas": 1
        },
        {
            "pron": "i",
            "verb": "think",
            "noun": "story",
            "det": "a",
            "adj": "good"
        }
    ],
    [
        "I had been taking the first thing",
        "maiṁ pahilī cīza lai rihā sī",
        "ਮੈਂ ਪਹਿਲੀ ਚੀਜ਼ ਲੈ ਰਿਹਾ ਸੀ",
        "I had been taking the first thing",
        {
            "en-en": 0,
            "pa-en": 1,
            "pa-pa": 2,
            "en-pa": 3
        },
        {
            "form": "past",
            "continuous": true,
            "perfect": true,
            "plural": false,
            "fem": 1,
            "mas": 1
        },
        {
            "pron": "i",
            "verb": "think",
            "noun": "story",
            "det": "the",
            "adj": "first"
        }
    ],
    [
        "I had been taking a many things",
        "maiṁ bahuta sārī'āṁ cīzāṁ lai rihā sī",
        "ਮੈਂ ਬਹੁਤ ਸਾਰੀਆਂ ਚੀਜ਼ਾਂ ਲੈ ਰਿਹਾ ਸੀ",
        "I had been taking a many things",
        {
            "en-en": 0,
            "pa-en": 1,
            "pa-pa": 2,
            "en-pa": 3
        },
        {
            "form": "past",
            "continuous": true,
            "perfect": true,
            "plural": false,
            "fem": 1,
            "mas": 1
        },
        {
            "pron": "i",
            "verb": "think",
            "noun": "story",
            "det": "a",
            "adj": "many"
        }
    ],
    [
        "I had been taking each thing",
        "maiṁ hara cīza laindā rihā sī",
        "ਮੈਂ ਹਰ ਚੀਜ਼ ਲੈਂਦਾ ਰਿਹਾ ਸੀ",
        "I had been taking each thing",
        {
            "en-en": 0,
            "pa-en": 1,
            "pa-pa": 2,
            "en-pa": 3
        },
        {
            "form": "past",
            "continuous": true,
            "perfect": true,
            "plural": false,
            "fem": 1,
            "mas": 1
        },
        {
            "pron": "i",
            "verb": "think",
            "noun": "story",
            "adj": "each"
        }
    ],
    [
        "I had been taking good time",
        "maiṁ cagā samāṁ ka. Rihā sī",
        "ਮੈਂ ਚੰਗਾ ਸਮਾਂ ਕੱ. ਰਿਹਾ ਸੀ",
        "I had been taking good time",
        {
            "en-en": 0,
            "pa-en": 1,
            "pa-pa": 2,
            "en-pa": 3
        },
        {
            "form": "past",
            "continuous": true,
            "perfect": true,
            "plural": false,
            "fem": 1,
            "mas": 1
        },
        {
            "pron": "i",
            "verb": "think",
            "noun": "work",
            "adj": "good"
        }
    ],
    [
        "I had been taking the first time",
        "maiṁ pahilī vāra lai rihā sī",
        "ਮੈਂ ਪਹਿਲੀ ਵਾਰ ਲੈ ਰਿਹਾ ਸੀ",
        "I had been taking the first time",
        {
            "en-en": 0,
            "pa-en": 1,
            "pa-pa": 2,
            "en-pa": 3
        },
        {
            "form": "past",
            "continuous": true,
            "perfect": true,
            "plural": false,
            "fem": 1,
            "mas": 1
        },
        {
            "pron": "i",
            "verb": "think",
            "noun": "work",
            "det": "the",
            "adj": "first"
        }
    ],
    [
        "I had been taking many times",
        "maiṁ ka'ī vāra laindā rihā sī",
        "ਮੈਂ ਕਈ ਵਾਰ ਲੈਂਦਾ ਰਿਹਾ ਸੀ",
        "I had been taking many times",
        {
            "en-en": 0,
            "pa-en": 1,
            "pa-pa": 2,
            "en-pa": 3
        },
        {
            "form": "past",
            "continuous": true,
            "perfect": true,
            "plural": false,
            "fem": 1,
            "mas": 1
        },
        {
            "pron": "i",
            "verb": "think",
            "noun": "work",
            "adj": "each"
        }
    ],
    [
        "I had been seeing a good book",
        "maiṁ ika cagī kitāba vēkha rahī sī",
        "ਮੈਂ ਇਕ ਚੰਗੀ ਕਿਤਾਬ ਵੇਖ ਰਹੀ ਸੀ",
        "I had been seeing a good book",
        {
            "en-en": 0,
            "pa-en": 1,
            "pa-pa": 2,
            "en-pa": 3
        },
        {
            "form": "past",
            "continuous": true,
            "perfect": true,
            "plural": false,
            "fem": 1,
            "mas": 1
        },
        {
            "pron": "i",
            "verb": "look",
            "noun": "business",
            "det": "a",
            "adj": "good"
        }
    ],
    [
        "I had been seeing each book",
        "maiṁ hara kitāba vēkha rihā sī",
        "ਮੈਂ ਹਰ ਕਿਤਾਬ ਵੇਖ ਰਿਹਾ ਸੀ",
        "I had been seeing each book",
        {
            "en-en": 0,
            "pa-en": 1,
            "pa-pa": 2,
            "en-pa": 3
        },
        {
            "form": "past",
            "continuous": true,
            "perfect": true,
            "plural": false,
            "fem": 1,
            "mas": 1
        },
        {
            "pron": "i",
            "verb": "look",
            "noun": "business",
            "adj": "each"
        }
    ],
    [
        "I had been seeing the many countries",
        "maiṁ bahuta sārē dēśāṁ nū vēkha rihā sī",
        "ਮੈਂ ਬਹੁਤ ਸਾਰੇ ਦੇਸ਼ਾਂ ਨੂੰ ਵੇਖ ਰਿਹਾ ਸੀ",
        "I had been seeing the many countries",
        {
            "en-en": 0,
            "pa-en": 1,
            "pa-pa": 2,
            "en-pa": 3
        },
        {
            "form": "past",
            "continuous": true,
            "perfect": true,
            "plural": false,
            "fem": 1,
            "mas": 1
        },
        {
            "pron": "i",
            "verb": "look",
            "noun": "family",
            "det": "the",
            "adj": "first"
        }
    ],
    [
        "I had been seeing each country",
        "maiṁ hara dēśa nū vēkhadā rihā sī",
        "ਮੈਂ ਹਰ ਦੇਸ਼ ਨੂੰ ਵੇਖਦਾ ਰਿਹਾ ਸੀ",
        "I had been seeing each country",
        {
            "en-en": 0,
            "pa-en": 1,
            "pa-pa": 2,
            "en-pa": 3
        },
        {
            "form": "past",
            "continuous": true,
            "perfect": true,
            "plural": false,
            "fem": 1,
            "mas": 1
        },
        {
            "pron": "i",
            "verb": "look",
            "noun": "family",
            "det": "my",
            "adj": "many"
        }
    ],
    [
        "I had been seeing the first family",
        "maiṁ pahilē parivāra nū vēkha rihā sī",
        "ਮੈਂ ਪਹਿਲੇ ਪਰਿਵਾਰ ਨੂੰ ਵੇਖ ਰਿਹਾ ਸੀ",
        "I had been seeing the first family",
        {
            "en-en": 0,
            "pa-en": 1,
            "pa-pa": 2,
            "en-pa": 3
        },
        {
            "form": "past",
            "continuous": true,
            "perfect": true,
            "plural": false,
            "fem": 1,
            "mas": 1
        },
        {
            "pron": "i",
            "verb": "look",
            "noun": "family",
            "adj": "each"
        }
    ],
    [
        "I had been seeing each group",
        "maiṁ hara samūha nū vēkhadā rihā sī",
        "ਮੈਂ ਹਰ ਸਮੂਹ ਨੂੰ ਵੇਖਦਾ ਰਿਹਾ ਸੀ",
        "I had been seeing each group",
        {
            "en-en": 0,
            "pa-en": 1,
            "pa-pa": 2,
            "en-pa": 3
        },
        {
            "form": "past",
            "continuous": true,
            "perfect": true,
            "plural": false,
            "fem": 1,
            "mas": 1
        },
        {
            "pron": "i",
            "verb": "look",
            "noun": "mother",
            "det": "the",
            "adj": "first"
        }
    ],
    [
        "I had been seeing a many hands",
        "maiṁ bahuta sārē hatha vēkhadā rihā sī",
        "ਮੈਂ ਬਹੁਤ ਸਾਰੇ ਹੱਥ ਵੇਖਦਾ ਰਿਹਾ ਸੀ",
        "I had been seeing a many hands",
        {
            "en-en": 0,
            "pa-en": 1,
            "pa-pa": 2,
            "en-pa": 3
        },
        {
            "form": "past",
            "continuous": true,
            "perfect": true,
            "plural": false,
            "fem": 1,
            "mas": 1
        },
        {
            "pron": "i",
            "verb": "look",
            "noun": "mother",
            "det": "my",
            "adj": "many"
        }
    ],
    [
        "I had been seeing each hand",
        "maiṁ hara ika hatha vēkha rihā sī",
        "ਮੈਂ ਹਰ ਇਕ ਹੱਥ ਵੇਖ ਰਿਹਾ ਸੀ",
        "I had been seeing each hand",
        {
            "en-en": 0,
            "pa-en": 1,
            "pa-pa": 2,
            "en-pa": 3
        },
        {
            "form": "past",
            "continuous": true,
            "perfect": true,
            "plural": false,
            "fem": 1,
            "mas": 1
        },
        {
            "pron": "i",
            "verb": "look",
            "noun": "mother",
            "adj": "each"
        }
    ],
    [
        "I had been seeing a first home",
        "maiṁ pahilāṁ ghara vēkhi'ā hō'i'ā sī",
        "ਮੈਂ ਪਹਿਲਾਂ ਘਰ ਵੇਖਿਆ ਹੋਇਆ ਸੀ",
        "I had been seeing a first home",
        {
            "en-en": 0,
            "pa-en": 1,
            "pa-pa": 2,
            "en-pa": 3
        },
        {
            "form": "past",
            "continuous": true,
            "perfect": true,
            "plural": false,
            "fem": 1,
            "mas": 1
        },
        {
            "pron": "i",
            "verb": "look",
            "noun": "people",
            "det": "the",
            "adj": "first"
        }
    ],
    [
        "I had been seeing a many home",
        "maiṁ bahuta sārā ghara vēkhadā rihā sī",
        "ਮੈਂ ਬਹੁਤ ਸਾਰਾ ਘਰ ਵੇਖਦਾ ਰਿਹਾ ਸੀ",
        "I had been seeing a many home",
        {
            "en-en": 0,
            "pa-en": 1,
            "pa-pa": 2,
            "en-pa": 3
        },
        {
            "form": "past",
            "continuous": true,
            "perfect": true,
            "plural": false,
            "fem": 1,
            "mas": 1
        },
        {
            "pron": "i",
            "verb": "look",
            "noun": "people",
            "adj": "many"
        }
    ],
    [
        "I had been seeing a many men",
        "maiṁ bahuta sārē ādamī vēkhadā rihā sī",
        "ਮੈਂ ਬਹੁਤ ਸਾਰੇ ਆਦਮੀ ਵੇਖਦਾ ਰਿਹਾ ਸੀ",
        "I had been seeing a many men",
        {
            "en-en": 0,
            "pa-en": 1,
            "pa-pa": 2,
            "en-pa": 3
        },
        {
            "form": "past",
            "continuous": true,
            "perfect": true,
            "plural": false,
            "fem": 1,
            "mas": 1
        },
        {
            "pron": "i",
            "verb": "look",
            "noun": "woman",
            "det": "the",
            "adj": "first"
        }
    ],
    [
        "I had been seeing each man",
        "maiṁ hara ādamī nū vēkhadā rihā sī",
        "ਮੈਂ ਹਰ ਆਦਮੀ ਨੂੰ ਵੇਖਦਾ ਰਿਹਾ ਸੀ",
        "I had been seeing each man",
        {
            "en-en": 0,
            "pa-en": 1,
            "pa-pa": 2,
            "en-pa": 3
        },
        {
            "form": "past",
            "continuous": true,
            "perfect": true,
            "plural": false,
            "fem": 1,
            "mas": 1
        },
        {
            "pron": "i",
            "verb": "look",
            "noun": "woman",
            "det": "a",
            "adj": "many"
        }
    ],
    [
        "I had been seeing the first mother",
        "maiṁ pahilī māṁ nū vēkhadī rahī sī",
        "ਮੈਂ ਪਹਿਲੀ ਮਾਂ ਨੂੰ ਵੇਖਦੀ ਰਹੀ ਸੀ",
        "I had been seeing the first mother",
        {
            "en-en": 0,
            "pa-en": 1,
            "pa-pa": 2,
            "en-pa": 3
        },
        {
            "form": "past",
            "continuous": true,
            "perfect": true,
            "plural": false,
            "fem": 1,
            "mas": 1
        },
        {
            "pron": "i",
            "verb": "look",
            "noun": "woman",
            "adj": "each"
        }
    ],
    [
        "I had been seeing my many mothers",
        "maiṁ āpaṇī'āṁ bahuta sārī'āṁ māvāṁ nū vēkhadā rihā sī",
        "ਮੈਂ ਆਪਣੀਆਂ ਬਹੁਤ ਸਾਰੀਆਂ ਮਾਵਾਂ ਨੂੰ ਵੇਖਦਾ ਰਿਹਾ ਸੀ",
        "I had been seeing my many mothers",
        {
            "en-en": 0,
            "pa-en": 1,
            "pa-pa": 2,
            "en-pa": 3
        },
        {
            "form": "past",
            "continuous": true,
            "perfect": true,
            "plural": false,
            "fem": 1,
            "mas": 1
        },
        {
            "pron": "i",
            "verb": "look",
            "noun": "work",
            "adj": "good"
        }
    ],
    [
        "I had been seeing each mother",
        "maiṁ hara māṁ nū vēkhadā rihā sī",
        "ਮੈਂ ਹਰ ਮਾਂ ਨੂੰ ਵੇਖਦਾ ਰਿਹਾ ਸੀ",
        "I had been seeing each mother",
        {
            "en-en": 0,
            "pa-en": 1,
            "pa-pa": 2,
            "en-pa": 3
        },
        {
            "form": "past",
            "continuous": true,
            "perfect": true,
            "plural": false,
            "fem": 1,
            "mas": 1
        },
        {
            "pron": "i",
            "verb": "look",
            "noun": "work",
            "det": "the",
            "adj": "first"
        }
    ],
    [
        "I had been seeing the first people",
        "maiṁ pahilē lōkāṁ nū vēkhadā rihā sī",
        "ਮੈਂ ਪਹਿਲੇ ਲੋਕਾਂ ਨੂੰ ਵੇਖਦਾ ਰਿਹਾ ਸੀ",
        "I had been seeing the first people",
        {
            "en-en": 0,
            "pa-en": 1,
            "pa-pa": 2,
            "en-pa": 3
        },
        {
            "form": "past",
            "continuous": true,
            "perfect": true,
            "plural": false,
            "fem": 1,
            "mas": 1
        },
        {
            "pron": "i",
            "verb": "look",
            "noun": "work",
            "adj": "each"
        }
    ],
    [
        "I had been seeing the first point",
        "maiṁ pahilā bidū vēkha rihā sī",
        "ਮੈਂ ਪਹਿਲਾ ਬਿੰਦੂ ਵੇਖ ਰਿਹਾ ਸੀ",
        "I had been seeing the first point",
        {
            "en-en": 0,
            "pa-en": 1,
            "pa-pa": 2,
            "en-pa": 3
        },
        {
            "form": "past",
            "continuous": true,
            "perfect": true,
            "plural": false,
            "fem": 1,
            "mas": 1
        },
        {
            "pron": "i",
            "verb": "want",
            "noun": "day",
            "det": "a",
            "adj": "good"
        }
    ],
    [
        "I had been seeing a many points",
        "maiṁ bahuta sārē nukatē vēkhadā rihā sī",
        "ਮੈਂ ਬਹੁਤ ਸਾਰੇ ਨੁਕਤੇ ਵੇਖਦਾ ਰਿਹਾ ਸੀ",
        "I had been seeing a many points",
        {
            "en-en": 0,
            "pa-en": 1,
            "pa-pa": 2,
            "en-pa": 3
        },
        {
            "form": "past",
            "continuous": true,
            "perfect": true,
            "plural": false,
            "fem": 1,
            "mas": 1
        },
        {
            "pron": "i",
            "verb": "want",
            "noun": "day",
            "det": "the",
            "adj": "first"
        }
    ],
    [
        "I had been seeing each point",
        "maiṁ hara nukatā vēkha rihā sī",
        "ਮੈਂ ਹਰ ਨੁਕਤਾ ਵੇਖ ਰਿਹਾ ਸੀ",
        "I had been seeing each point",
        {
            "en-en": 0,
            "pa-en": 1,
            "pa-pa": 2,
            "en-pa": 3
        },
        {
            "form": "past",
            "continuous": true,
            "perfect": true,
            "plural": false,
            "fem": 1,
            "mas": 1
        },
        {
            "pron": "i",
            "verb": "want",
            "noun": "day",
            "det": "a",
            "adj": "many"
        }
    ],
    [
        "I had been seeing the first problem",
        "maiṁ pahilī samasi'ā vēkha rihā sī",
        "ਮੈਂ ਪਹਿਲੀ ਸਮੱਸਿਆ ਵੇਖ ਰਿਹਾ ਸੀ",
        "I had been seeing the first problem",
        {
            "en-en": 0,
            "pa-en": 1,
            "pa-pa": 2,
            "en-pa": 3
        },
        {
            "form": "past",
            "continuous": true,
            "perfect": true,
            "plural": false,
            "fem": 1,
            "mas": 1
        },
        {
            "pron": "i",
            "verb": "want",
            "noun": "day",
            "adj": "each"
        }
    ],
    [
        "I had been seeing a many problems",
        "maiṁ bahuta sārī'āṁ muśakalāṁ vēkha rihā sī",
        "ਮੈਂ ਬਹੁਤ ਸਾਰੀਆਂ ਮੁਸ਼ਕਲਾਂ ਵੇਖ ਰਿਹਾ ਸੀ",
        "I had been seeing a many problems",
        {
            "en-en": 0,
            "pa-en": 1,
            "pa-pa": 2,
            "en-pa": 3
        },
        {
            "form": "past",
            "continuous": true,
            "perfect": true,
            "plural": false,
            "fem": 1,
            "mas": 1
        },
        {
            "pron": "i",
            "verb": "want",
            "noun": "family",
            "det": "the",
            "adj": "first"
        }
    ],
    [
        "I had been seeing each problem",
        "maiṁ hara samasi'ā nū vēkhadā rihā sī",
        "ਮੈਂ ਹਰ ਸਮੱਸਿਆ ਨੂੰ ਵੇਖਦਾ ਰਿਹਾ ਸੀ",
        "I had been seeing each problem",
        {
            "en-en": 0,
            "pa-en": 1,
            "pa-pa": 2,
            "en-pa": 3
        },
        {
            "form": "past",
            "continuous": true,
            "perfect": true,
            "plural": false,
            "fem": 1,
            "mas": 1
        },
        {
            "pron": "i",
            "verb": "want",
            "noun": "family",
            "det": "my",
            "adj": "many"
        }
    ],
    [
        "I had been seeing the first room",
        "maiṁ pahilē kamarē nū vēkhi'ā hō'i'ā sī",
        "ਮੈਂ ਪਹਿਲੇ ਕਮਰੇ ਨੂੰ ਵੇਖਿਆ ਹੋਇਆ ਸੀ",
        "I had been seeing the first room",
        {
            "en-en": 0,
            "pa-en": 1,
            "pa-pa": 2,
            "en-pa": 3
        },
        {
            "form": "past",
            "continuous": true,
            "perfect": true,
            "plural": false,
            "fem": 1,
            "mas": 1
        },
        {
            "pron": "i",
            "verb": "want",
            "noun": "family",
            "adj": "each"
        }
    ],
    [
        "I had been seeing a many rooms",
        "maiṁ bahuta sārē kamarē vēkha rihā sī",
        "ਮੈਂ ਬਹੁਤ ਸਾਰੇ ਕਮਰੇ ਵੇਖ ਰਿਹਾ ਸੀ",
        "I had been seeing a many rooms",
        {
            "en-en": 0,
            "pa-en": 1,
            "pa-pa": 2,
            "en-pa": 3
        },
        {
            "form": "past",
            "continuous": true,
            "perfect": true,
            "plural": false,
            "fem": 1,
            "mas": 1
        },
        {
            "pron": "i",
            "verb": "want",
            "noun": "group",
            "det": "the",
            "adj": "first"
        }
    ],
    [
        "I had been seeing each room",
        "maiṁ hara kamarā vēkhadā rihā sī",
        "ਮੈਂ ਹਰ ਕਮਰਾ ਵੇਖਦਾ ਰਿਹਾ ਸੀ",
        "I had been seeing each room",
        {
            "en-en": 0,
            "pa-en": 1,
            "pa-pa": 2,
            "en-pa": 3
        },
        {
            "form": "past",
            "continuous": true,
            "perfect": true,
            "plural": false,
            "fem": 1,
            "mas": 1
        },
        {
            "pron": "i",
            "verb": "want",
            "noun": "group",
            "det": "the",
            "adj": "many"
        }
    ],
    [
        "I had been seeing a good student",
        "maiṁ ika cagā vidi'ārathī vēkhadā rihā sī",
        "ਮੈਂ ਇੱਕ ਚੰਗਾ ਵਿਦਿਆਰਥੀ ਵੇਖਦਾ ਰਿਹਾ ਸੀ",
        "I had been seeing a good student",
        {
            "en-en": 0,
            "pa-en": 1,
            "pa-pa": 2,
            "en-pa": 3
        },
        {
            "form": "past",
            "continuous": true,
            "perfect": true,
            "plural": false,
            "fem": 1,
            "mas": 1
        },
        {
            "pron": "i",
            "verb": "want",
            "noun": "group",
            "adj": "each"
        }
    ],
    [
        "I had been seeing a good thing",
        "maiṁ ika cagī cīza vēkha rihā sī",
        "ਮੈਂ ਇੱਕ ਚੰਗੀ ਚੀਜ਼ ਵੇਖ ਰਿਹਾ ਸੀ",
        "I had been seeing a good thing",
        {
            "en-en": 0,
            "pa-en": 1,
            "pa-pa": 2,
            "en-pa": 3
        },
        {
            "form": "past",
            "continuous": true,
            "perfect": true,
            "plural": false,
            "fem": 1,
            "mas": 1
        },
        {
            "pron": "i",
            "verb": "want",
            "noun": "job",
            "det": "the",
            "adj": "first"
        }
    ],
    [
        "I had been seeing the first thing",
        "maiṁ pahilī cīza vēkha rihā sī",
        "ਮੈਂ ਪਹਿਲੀ ਚੀਜ਼ ਵੇਖ ਰਿਹਾ ਸੀ",
        "I had been seeing the first thing",
        {
            "en-en": 0,
            "pa-en": 1,
            "pa-pa": 2,
            "en-pa": 3
        },
        {
            "form": "past",
            "continuous": true,
            "perfect": true,
            "plural": false,
            "fem": 1,
            "mas": 1
        },
        {
            "pron": "i",
            "verb": "want",
            "noun": "job",
            "det": "a",
            "adj": "many"
        }
    ],
    [
        "I had been seeing a many things",
        "maiṁ bahuta sārī'āṁ cīzāṁ vēkha rihā sī",
        "ਮੈਂ ਬਹੁਤ ਸਾਰੀਆਂ ਚੀਜ਼ਾਂ ਵੇਖ ਰਿਹਾ ਸੀ",
        "I had been seeing a many things",
        {
            "en-en": 0,
            "pa-en": 1,
            "pa-pa": 2,
            "en-pa": 3
        },
        {
            "form": "past",
            "continuous": true,
            "perfect": true,
            "plural": false,
            "fem": 1,
            "mas": 1
        },
        {
            "pron": "i",
            "verb": "want",
            "noun": "job",
            "adj": "each"
        }
    ],
    [
        "I had been seeing each woman",
        "maiṁ hara womanrata nū vēkhadā rihā sī",
        "ਮੈਂ ਹਰ womanਰਤ ਨੂੰ ਵੇਖਦਾ ਰਿਹਾ ਸੀ",
        "I had been seeing each woman",
        {
            "en-en": 0,
            "pa-en": 1,
            "pa-pa": 2,
            "en-pa": 3
        },
        {
            "form": "past",
            "continuous": true,
            "perfect": true,
            "plural": false,
            "fem": 1,
            "mas": 1
        },
        {
            "pron": "i",
            "verb": "want",
            "noun": "room",
            "det": "the",
            "adj": "first"
        }
    ],
    [
        "I had been seeing the first world",
        "maiṁ pahilē sasāra nū vēkha rihā sī",
        "ਮੈਂ ਪਹਿਲੇ ਸੰਸਾਰ ਨੂੰ ਵੇਖ ਰਿਹਾ ਸੀ",
        "I had been seeing the first world",
        {
            "en-en": 0,
            "pa-en": 1,
            "pa-pa": 2,
            "en-pa": 3
        },
        {
            "form": "past",
            "continuous": true,
            "perfect": true,
            "plural": false,
            "fem": 1,
            "mas": 1
        },
        {
            "pron": "i",
            "verb": "want",
            "noun": "room",
            "det": "a",
            "adj": "many"
        }
    ],
    [
        "I had been seeing the many worlds",
        "maiṁ bahuta sārē sasāra vēkhadā rihā sī",
        "ਮੈਂ ਬਹੁਤ ਸਾਰੇ ਸੰਸਾਰ ਵੇਖਦਾ ਰਿਹਾ ਸੀ",
        "I had been seeing the many worlds",
        {
            "en-en": 0,
            "pa-en": 1,
            "pa-pa": 2,
            "en-pa": 3
        },
        {
            "form": "past",
            "continuous": true,
            "perfect": true,
            "plural": false,
            "fem": 1,
            "mas": 1
        },
        {
            "pron": "i",
            "verb": "want",
            "noun": "room",
            "adj": "each"
        }
    ],
    [
        "I had been seeing each world",
        "maiṁ hara ika sasāra nū vēkhadā rihā sī",
        "ਮੈਂ ਹਰ ਇਕ ਸੰਸਾਰ ਨੂੰ ਵੇਖਦਾ ਰਿਹਾ ਸੀ",
        "I had been seeing each world",
        {
            "en-en": 0,
            "pa-en": 1,
            "pa-pa": 2,
            "en-pa": 3
        },
        {
            "form": "past",
            "continuous": true,
            "perfect": true,
            "plural": false,
            "fem": 1,
            "mas": 1
        },
        {
            "pron": "i",
            "verb": "want",
            "noun": "story",
            "det": "a",
            "adj": "good"
        }
    ],
    [
        "I had been coming to the many countries",
        "maiṁ bahuta sārē dēśāṁ vica ā'i'ā hō'i'ā sī",
        "ਮੈਂ ਬਹੁਤ ਸਾਰੇ ਦੇਸ਼ਾਂ ਵਿਚ ਆਇਆ ਹੋਇਆ ਸੀ",
        "I had been coming to the many countries",
        {
            "en-en": 0,
            "pa-en": 1,
            "pa-pa": 2,
            "en-pa": 3
        },
        {
            "form": "past",
            "continuous": true,
            "perfect": true,
            "plural": false,
            "fem": 1,
            "mas": 1
        },
        {
            "pron": "i",
            "verb": "want",
            "noun": "story",
            "det": "the",
            "adj": "first"
        }
    ],
    [
        "I had been coming to each country",
        "maiṁ hara dēśa ā'i'ā hō'i'ā sī",
        "ਮੈਂ ਹਰ ਦੇਸ਼ ਆਇਆ ਹੋਇਆ ਸੀ",
        "I had been coming to each country",
        {
            "en-en": 0,
            "pa-en": 1,
            "pa-pa": 2,
            "en-pa": 3
        },
        {
            "form": "past",
            "continuous": true,
            "perfect": true,
            "plural": false,
            "fem": 1,
            "mas": 1
        },
        {
            "pron": "i",
            "verb": "want",
            "noun": "story",
            "det": "a",
            "adj": "many"
        }
    ],
    [
        "I had been coming to the first family",
        "maiṁ pahilē parivāra kōla ā'i'ā hō'i'ā sī",
        "ਮੈਂ ਪਹਿਲੇ ਪਰਿਵਾਰ ਕੋਲ ਆਇਆ ਹੋਇਆ ਸੀ",
        "I had been coming to the first family",
        {
            "en-en": 0,
            "pa-en": 1,
            "pa-pa": 2,
            "en-pa": 3
        },
        {
            "form": "past",
            "continuous": true,
            "perfect": true,
            "plural": false,
            "fem": 1,
            "mas": 1
        },
        {
            "pron": "i",
            "verb": "want",
            "noun": "story",
            "adj": "each"
        }
    ],
    [
        "I had been coming from each group",
        "maiṁ harēka samūha tōṁ ā'i'ā hō'i'ā sī",
        "ਮੈਂ ਹਰੇਕ ਸਮੂਹ ਤੋਂ ਆਇਆ ਹੋਇਆ ਸੀ",
        "I had been coming from each group",
        {
            "en-en": 0,
            "pa-en": 1,
            "pa-pa": 2,
            "en-pa": 3
        },
        {
            "form": "past",
            "continuous": true,
            "perfect": true,
            "plural": false,
            "fem": 1,
            "mas": 1
        },
        {
            "pron": "i",
            "verb": "want",
            "noun": "thing",
            "det": "a",
            "adj": "good"
        }
    ],
    [
        "I had been coming the first home",
        "maiṁ pahilē ghara ā'i'ā hō'i'ā sī",
        "ਮੈਂ ਪਹਿਲੇ ਘਰ ਆਇਆ ਹੋਇਆ ਸੀ",
        "I had been coming the first home",
        {
            "en-en": 0,
            "pa-en": 1,
            "pa-pa": 2,
            "en-pa": 3
        },
        {
            "form": "past",
            "continuous": true,
            "perfect": true,
            "plural": false,
            "fem": 1,
            "mas": 1
        },
        {
            "pron": "i",
            "verb": "want",
            "noun": "thing",
            "det": "the",
            "adj": "first"
        }
    ],
    [
        "I had been coming many home",
        "maiṁ bahuta sārē ghara ā rihā sī",
        "ਮੈਂ ਬਹੁਤ ਸਾਰੇ ਘਰ ਆ ਰਿਹਾ ਸੀ",
        "I had been coming many home",
        {
            "en-en": 0,
            "pa-en": 1,
            "pa-pa": 2,
            "en-pa": 3
        },
        {
            "form": "past",
            "continuous": true,
            "perfect": true,
            "plural": false,
            "fem": 1,
            "mas": 1
        },
        {
            "pron": "i",
            "verb": "want",
            "noun": "thing",
            "det": "a",
            "adj": "many"
        }
    ],
    [
        "I had been coming each home",
        "maiṁ hara ghara ā'i'ā hō'i'ā sī",
        "ਮੈਂ ਹਰ ਘਰ ਆਇਆ ਹੋਇਆ ਸੀ",
        "I had been coming each home",
        {
            "en-en": 0,
            "pa-en": 1,
            "pa-pa": 2,
            "en-pa": 3
        },
        {
            "form": "past",
            "continuous": true,
            "perfect": true,
            "plural": false,
            "fem": 1,
            "mas": 1
        },
        {
            "pron": "i",
            "verb": "want",
            "noun": "thing",
            "adj": "each"
        }
    ],
    [
        "I had been coming to the first school",
        "maiṁ pahilē sakūla ā'i'ā hō'i'ā sī",
        "ਮੈਂ ਪਹਿਲੇ ਸਕੂਲ ਆਇਆ ਹੋਇਆ ਸੀ",
        "I had been coming to the first school",
        {
            "en-en": 0,
            "pa-en": 1,
            "pa-pa": 2,
            "en-pa": 3
        },
        {
            "form": "past",
            "continuous": true,
            "perfect": true,
            "plural": false,
            "fem": 1,
            "mas": 1
        },
        {
            "pron": "i",
            "verb": "want",
            "noun": "work",
            "adj": "good"
        }
    ],
    [
        "I had been coming to many schools",
        "maiṁ bahuta sārē sakūlāṁ vica ā'i'ā hō'i'ā sī",
        "ਮੈਂ ਬਹੁਤ ਸਾਰੇ ਸਕੂਲਾਂ ਵਿਚ ਆਇਆ ਹੋਇਆ ਸੀ",
        "I had been coming to many schools",
        {
            "en-en": 0,
            "pa-en": 1,
            "pa-pa": 2,
            "en-pa": 3
        },
        {
            "form": "past",
            "continuous": true,
            "perfect": true,
            "plural": false,
            "fem": 1,
            "mas": 1
        },
        {
            "pron": "i",
            "verb": "want",
            "noun": "work",
            "det": "the",
            "adj": "first"
        }
    ],
    [
        "I had been coming to each school",
        "maiṁ hara sakūla ā rihā sī",
        "ਮੈਂ ਹਰ ਸਕੂਲ ਆ ਰਿਹਾ ਸੀ",
        "I had been coming to each school",
        {
            "en-en": 0,
            "pa-en": 1,
            "pa-pa": 2,
            "en-pa": 3
        },
        {
            "form": "past",
            "continuous": true,
            "perfect": true,
            "plural": false,
            "fem": 1,
            "mas": 1
        },
        {
            "pron": "i",
            "verb": "want",
            "noun": "work",
            "adj": "each"
        }
    ],
    [
        "I had been telling a many women",
        "Maiṁ bahuta sārī'āṁ.Ratāṁ nū kahidā rihā sī",
        "ਮੈਂ ਬਹੁਤ ਸਾਰੀਆਂ .ਰਤਾਂ ਨੂੰ ਕਹਿੰਦਾ ਰਿਹਾ ਸੀ",
        "I had been telling a many women",
        {
            "en-en": 0,
            "pa-en": 1,
            "pa-pa": 2,
            "en-pa": 3
        },
        {
            "form": "past",
            "continuous": true,
            "perfect": true,
            "plural": false,
            "fem": 1,
            "mas": 1
        },
        {
            "pron": "i",
            "verb": "give",
            "noun": "thing",
            "det": "a",
            "adj": "good"
        }
    ],
    [
        "I had been telling each woman",
        "maiṁ harēka tellingrata nū kahidā rihā sī",
        "ਮੈਂ ਹਰੇਕ tellingਰਤ ਨੂੰ ਕਹਿੰਦਾ ਰਿਹਾ ਸੀ",
        "I had been telling each woman",
        {
            "en-en": 0,
            "pa-en": 1,
            "pa-pa": 2,
            "en-pa": 3
        },
        {
            "form": "past",
            "continuous": true,
            "perfect": true,
            "plural": false,
            "fem": 1,
            "mas": 1
        },
        {
            "pron": "i",
            "verb": "give",
            "noun": "thing",
            "det": "the",
            "adj": "first"
        }
    ],
    [
        "I had been telling a good word",
        "maiṁ ika cagā śabada kahi rihā sī",
        "ਮੈਂ ਇਕ ਚੰਗਾ ਸ਼ਬਦ ਕਹਿ ਰਿਹਾ ਸੀ",
        "I had been telling a good word",
        {
            "en-en": 0,
            "pa-en": 1,
            "pa-pa": 2,
            "en-pa": 3
        },
        {
            "form": "past",
            "continuous": true,
            "perfect": true,
            "plural": false,
            "fem": 1,
            "mas": 1
        },
        {
            "pron": "i",
            "verb": "give",
            "noun": "thing",
            "det": "a",
            "adj": "many"
        }
    ],
    [
        "I had been telling the first word",
        "maiṁ pahilā śabada kahi rihā sī",
        "ਮੈਂ ਪਹਿਲਾ ਸ਼ਬਦ ਕਹਿ ਰਿਹਾ ਸੀ",
        "I had been telling the first word",
        {
            "en-en": 0,
            "pa-en": 1,
            "pa-pa": 2,
            "en-pa": 3
        },
        {
            "form": "past",
            "continuous": true,
            "perfect": true,
            "plural": false,
            "fem": 1,
            "mas": 1
        },
        {
            "pron": "i",
            "verb": "give",
            "noun": "thing",
            "adj": "each"
        }
    ],
    [
        "I had been having the first school",
        "mērā pahilā sakūla rihā sī",
        "ਮੇਰਾ ਪਹਿਲਾ ਸਕੂਲ ਰਿਹਾ ਸੀ",
        "I had been having the first school",
        {
            "en-en": 0,
            "pa-en": 1,
            "pa-pa": 2,
            "en-pa": 3
        },
        {
            "form": "past",
            "continuous": true,
            "perfect": true,
            "plural": false,
            "fem": 1,
            "mas": 1
        },
        {
            "pron": "i",
            "verb": "work",
            "noun": "day",
            "det": "a",
            "adj": "good"
        }
    ],
    [
        "I had been having many schools",
        "mērē kōla bahuta sārē sakūla sana",
        "ਮੇਰੇ ਕੋਲ ਬਹੁਤ ਸਾਰੇ ਸਕੂਲ ਸਨ",
        "I had been having many schools",
        {
            "en-en": 0,
            "pa-en": 1,
            "pa-pa": 2,
            "en-pa": 3
        },
        {
            "form": "past",
            "continuous": true,
            "perfect": true,
            "plural": false,
            "fem": 1,
            "mas": 1
        },
        {
            "pron": "i",
            "verb": "work",
            "noun": "day",
            "det": "the",
            "adj": "first"
        }
    ],
    [
        "I had been having each school",
        "mērā hara sakūla hudā sī",
        "ਮੇਰਾ ਹਰ ਸਕੂਲ ਹੁੰਦਾ ਸੀ",
        "I had been having each school",
        {
            "en-en": 0,
            "pa-en": 1,
            "pa-pa": 2,
            "en-pa": 3
        },
        {
            "form": "past",
            "continuous": true,
            "perfect": true,
            "plural": false,
            "fem": 1,
            "mas": 1
        },
        {
            "pron": "i",
            "verb": "work",
            "noun": "day",
            "det": "a",
            "adj": "many"
        }
    ],
    [
        "I had been having a good story",
        "mērī cagī kahāṇī rahī sī",
        "ਮੇਰੀ ਚੰਗੀ ਕਹਾਣੀ ਰਹੀ ਸੀ",
        "I had been having a good story",
        {
            "en-en": 0,
            "pa-en": 1,
            "pa-pa": 2,
            "en-pa": 3
        },
        {
            "form": "past",
            "continuous": true,
            "perfect": true,
            "plural": false,
            "fem": 1,
            "mas": 1
        },
        {
            "pron": "i",
            "verb": "work",
            "noun": "day",
            "adj": "each"
        }
    ],
    [
        "I had been having the first story",
        "mērī pahilī kahāṇī rahī sī",
        "ਮੇਰੀ ਪਹਿਲੀ ਕਹਾਣੀ ਰਹੀ ਸੀ",
        "I had been having the first story",
        {
            "en-en": 0,
            "pa-en": 1,
            "pa-pa": 2,
            "en-pa": 3
        },
        {
            "form": "past",
            "continuous": true,
            "perfect": true,
            "plural": false,
            "fem": 1,
            "mas": 1
        },
        {
            "pron": "i",
            "verb": "work",
            "noun": "family",
            "det": "the",
            "adj": "first"
        }
    ],
    [
        "I had been having a many stories",
        "mērē kōla bahuta sārī'āṁ kahāṇī'āṁ ā'ī'āṁ sana",
        "ਮੇਰੇ ਕੋਲ ਬਹੁਤ ਸਾਰੀਆਂ ਕਹਾਣੀਆਂ ਆਈਆਂ ਸਨ",
        "I had been having a many stories",
        {
            "en-en": 0,
            "pa-en": 1,
            "pa-pa": 2,
            "en-pa": 3
        },
        {
            "form": "past",
            "continuous": true,
            "perfect": true,
            "plural": false,
            "fem": 1,
            "mas": 1
        },
        {
            "pron": "i",
            "verb": "work",
            "noun": "family",
            "det": "my",
            "adj": "many"
        }
    ],
    [
        "I had been having each story",
        "maiṁ hara ika kahāṇī kara rihā sī",
        "ਮੈਂ ਹਰ ਇਕ ਕਹਾਣੀ ਕਰ ਰਿਹਾ ਸੀ",
        "I had been having each story",
        {
            "en-en": 0,
            "pa-en": 1,
            "pa-pa": 2,
            "en-pa": 3
        },
        {
            "form": "past",
            "continuous": true,
            "perfect": true,
            "plural": false,
            "fem": 1,
            "mas": 1
        },
        {
            "pron": "i",
            "verb": "work",
            "noun": "family",
            "adj": "each"
        }
    ],
    [
        "I had been having a good system",
        "Mērē kōla ika cagā sisaṭama rihā sī",
        "ਮੇਰੇ ਕੋਲ ਇੱਕ ਚੰਗਾ ਸਿਸਟਮ ਰਿਹਾ ਸੀ",
        "I had been having a good system",
        {
            "en-en": 0,
            "pa-en": 1,
            "pa-pa": 2,
            "en-pa": 3
        },
        {
            "form": "past",
            "continuous": true,
            "perfect": true,
            "plural": false,
            "fem": 1,
            "mas": 1
        },
        {
            "pron": "i",
            "verb": "work",
            "noun": "group",
            "det": "the",
            "adj": "first"
        }
    ],
    [
        "I had been having the first system",
        "mērē kōla pahilā sisaṭama sī",
        "ਮੇਰੇ ਕੋਲ ਪਹਿਲਾ ਸਿਸਟਮ ਸੀ",
        "I had been having the first system",
        {
            "en-en": 0,
            "pa-en": 1,
            "pa-pa": 2,
            "en-pa": 3
        },
        {
            "form": "past",
            "continuous": true,
            "perfect": true,
            "plural": false,
            "fem": 1,
            "mas": 1
        },
        {
            "pron": "i",
            "verb": "work",
            "noun": "group",
            "det": "the",
            "adj": "many"
        }
    ],
    [
        "I had been having a many systems",
        "mērē kōla bahuta sārē sisaṭama sana",
        "ਮੇਰੇ ਕੋਲ ਬਹੁਤ ਸਾਰੇ ਸਿਸਟਮ ਸਨ",
        "I had been having a many systems",
        {
            "en-en": 0,
            "pa-en": 1,
            "pa-pa": 2,
            "en-pa": 3
        },
        {
            "form": "past",
            "continuous": true,
            "perfect": true,
            "plural": false,
            "fem": 1,
            "mas": 1
        },
        {
            "pron": "i",
            "verb": "work",
            "noun": "group",
            "adj": "each"
        }
    ],
    [
        "I had been having my first way",
        "maiṁ āpaṇā pahilā rasatā rihā sī",
        "ਮੈਂ ਆਪਣਾ ਪਹਿਲਾ ਰਸਤਾ ਰਿਹਾ ਸੀ",
        "I had been having my first way",
        {
            "en-en": 0,
            "pa-en": 1,
            "pa-pa": 2,
            "en-pa": 3
        },
        {
            "form": "past",
            "continuous": true,
            "perfect": true,
            "plural": false,
            "fem": 1,
            "mas": 1
        },
        {
            "pron": "i",
            "verb": "work",
            "noun": "people",
            "det": "the",
            "adj": "first"
        }
    ],
    [
        "I had been having my many ways",
        "mērē kōla bahuta sārē tarīkē sana",
        "ਮੇਰੇ ਕੋਲ ਬਹੁਤ ਸਾਰੇ ਤਰੀਕੇ ਸਨ",
        "I had been having my many ways",
        {
            "en-en": 0,
            "pa-en": 1,
            "pa-pa": 2,
            "en-pa": 3
        },
        {
            "form": "past",
            "continuous": true,
            "perfect": true,
            "plural": false,
            "fem": 1,
            "mas": 1
        },
        {
            "pron": "i",
            "verb": "work",
            "noun": "people",
            "adj": "many"
        }
    ]
]